litenai/__init__.cpython-310-x86_64-linux-gnu.so
litenai/action.cpython-310-x86_64-linux-gnu.so
litenai/chatbot.cpython-310-x86_64-linux-gnu.so
litenai/config.cpython-310-x86_64-linux-gnu.so
litenai/context.cpython-310-x86_64-linux-gnu.so
litenai/database.cpython-310-x86_64-linux-gnu.so
litenai/exceptions.cpython-310-x86_64-linux-gnu.so
litenai/http_request.cpython-310-x86_64-linux-gnu.so
litenai/kernel.cpython-310-x86_64-linux-gnu.so
litenai/litenapi.cpython-310-x86_64-linux-gnu.so
litenai/logger.cpython-310-x86_64-linux-gnu.so
litenai/masteragent.cpython-310-x86_64-linux-gnu.so
litenai/openaiclient.cpython-310-x86_64-linux-gnu.so
litenai/response.cpython-310-x86_64-linux-gnu.so
litenai/session.cpython-310-x86_64-linux-gnu.so
litenai/slackmessage.cpython-310-x86_64-linux-gnu.so
litenai/storage.cpython-310-x86_64-linux-gnu.so
litenai/utils.cpython-310-x86_64-linux-gnu.so
litenai/version.cpython-310-x86_64-linux-gnu.so
litenai-0.0.42.data/scripts/litenai-config.yml
litenai-0.0.42.data/scripts/litenapp.py
litenai-0.0.42.data/scripts/litenapp.sh
litenai-0.0.42.data/scripts/litenchat.py
litenai-0.0.42.data/scripts/litenchat.sh
litenai-0.0.42.data/scripts/slackapp.py
litenai-0.0.42.data/scripts/slackapp.sh
litenai-0.0.42.dist-info/LICENSE
litenai-0.0.42.dist-info/METADATA
litenai-0.0.42.dist-info/WHEEL
litenai-0.0.42.dist-info/top_level.txt
litenai-0.0.42.dist-info/zip-safe
litenai-0.0.42.dist-info/RECORD
