Metadata-Version: 2.1
Name: litenai
Version: 0.0.42
Summary: Python library for Liten AI Data platform
Author: HK Verma
Author-email: hkverma@litenai.com
Classifier: Programming Language :: Python :: 3
Classifier: License :: OSI Approved :: MIT License
Classifier: Operating System :: OS Independent
License-File: LICENSE
Requires-Dist: bokeh
Requires-Dist: botocore
Requires-Dist: boto3
Requires-Dist: flask
Requires-Dist: grpcio
Requires-Dist: grpcio-status
Requires-Dist: holoviews
Requires-Dist: hvplot
Requires-Dist: ipython
Requires-Dist: openai >=1.10.0
Requires-Dist: pandas
Requires-Dist: panel
Requires-Dist: protobuf
Requires-Dist: pyarrow ==14.0.2
Requires-Dist: pyspark ==3.5.0
Requires-Dist: pyyaml
Requires-Dist: slackclient
Requires-Dist: slackeventsapi
Requires-Dist: slack-bolt
Requires-Dist: tenacity
Requires-Dist: tiktoken
